SSTool/__init__.py
SSTool/__version__.py
SSTool/main.py
SSTool/engine/__init__.py
SSTool/engine/build.py
SSTool/engine/parse.py
SSTool/engine/stability.py
SSTool/engine/devices/C.py
SSTool/engine/devices/RL.py
SSTool/engine/devices/SG.py
SSTool/engine/devices/VSC.py
SSTool/engine/devices/__init__.py
SSTool/engine/devices/auxiliaries.py
SSTool-0.0.8.dist-info/LICENSE
SSTool-0.0.8.dist-info/METADATA
SSTool-0.0.8.dist-info/WHEEL
SSTool-0.0.8.dist-info/top_level.txt
SSTool-0.0.8.dist-info/RECORD
