Metadata-Version: 2.1
Name: SSTool
Version: 0.0.8
Summary: State Space Tool
Home-page: UNKNOWN
Author: Josep Fanals
Author-email: josep.fanals@upc.edu
License: UNKNOWN
Keywords: python,first package
Platform: UNKNOWN
Classifier: Development Status :: 3 - Alpha
Classifier: Intended Audience :: Developers
Classifier: Programming Language :: Python :: 3
Classifier: Operating System :: Unix
License-File: LICENSE
